mwviews/__init__.py
mwviews/mwviews.py
mwviews/page_view_count.py
mwviews/api/__init__.py
mwviews/api/pageviews.py
mwviews/utilities/__init__.py
mwviews/utilities/aggregate.py
mwviews/utilities/fetch_global_namespaces.py
mwviews/utilities/util.py
mwviews-0.2.1.dist-info/LICENSE.txt
mwviews-0.2.1.dist-info/METADATA
mwviews-0.2.1.dist-info/WHEEL
mwviews-0.2.1.dist-info/entry_points.txt
mwviews-0.2.1.dist-info/top_level.txt
mwviews-0.2.1.dist-info/RECORD
