Metadata-Version: 2.1
Name: mwviews
Version: 0.2.1
Summary: Tools for parsing and querying Wikimedia Foundation pageview data, from both static dumps and online API
Home-page: https://github.com/mediawiki-utilities/python-mwviews
Author: Dan Andreescu
Author-email: dandreescu@wikimedia.org
License: MIT
Keywords: gwikimedia,wikipedia,pageview,api
Platform: UNKNOWN
Requires-Python: >=3.0
License-File: LICENSE.txt
Requires-Dist: requests
Requires-Dist: more-itertools
Requires-Dist: docopt
Requires-Dist: mwcli
Requires-Dist: mwapi
